flashcrashed/__init__.py
flashcrashed/__main__.py
flashcrashed/cli.py
flashcrashed/detector.py
flashcrashed/flashcrashed.py
flashcrashed/market/__init__.py
flashcrashed/market/env.py
flashcrashed/market/gen.py
flashcrashed/market/real_crashes/ETPUSD1.csv
flashcrashed/market/real_crashes/NEOUSD1.csv
flashcrashed-0.1.3.dist-info/METADATA
flashcrashed-0.1.3.dist-info/RECORD
flashcrashed-0.1.3.dist-info/WHEEL
flashcrashed-0.1.3.dist-info/entry_points.txt
flashcrashed-0.1.3.dist-info/top_level.txt
