Metadata-Version: 2.1
Name: flashcrashed
Version: 0.1.3
Summary: Minimal library for detecting flash crashes in cryptocurrency prices on Bitfinex
Home-page: https://github.com/sentrip/flashcrashed
Author: Djordje Pepic
Author-email: djordje.m.pepic@gmail.com
License: GNU General Public License v3
Keywords: flashcrashed
Platform: UNKNOWN
Classifier: Development Status :: 2 - Pre-Alpha
Classifier: Intended Audience :: Developers
Classifier: License :: OSI Approved :: GNU General Public License v3 (GPLv3)
Classifier: Natural Language :: English
Classifier: Programming Language :: Python :: 3.5
Classifier: Programming Language :: Python :: 3.6
Requires-Dist: pandas (>=0.20.3)
Requires-Dist: numpy (>=1.13.3)
Requires-Dist: gym (>=0.9.4)
Requires-Dist: click (>=6.0)
Requires-Dist: btfx-trader (>=0.1.3)
Requires-Dist: pybeehive (>=0.1.4)
Requires-Dist: twilio (>=6.9.1)
